MANIFEST.in
README.txt
setup.cfg
setup.py
docs/CHANGES.txt
docs/CONTRIBUTORS.txt
docs/HISTORY.txt
docs/INSTALL.txt
docs/LICENSE.GPL
docs/LICENSE.txt
docs/README.txt
jalon/__init__.py
jalon.pas.bdd.egg-info/PKG-INFO
jalon.pas.bdd.egg-info/SOURCES.txt
jalon.pas.bdd.egg-info/dependency_links.txt
jalon.pas.bdd.egg-info/entry_points.txt
jalon.pas.bdd.egg-info/namespace_packages.txt
jalon.pas.bdd.egg-info/not-zip-safe
jalon.pas.bdd.egg-info/paster_plugins.txt
jalon.pas.bdd.egg-info/requires.txt
jalon.pas.bdd.egg-info/top_level.txt
jalon/pas/__init__.py
jalon/pas/bdd/README.txt
jalon/pas/bdd/__init__.py
jalon/pas/bdd/configure.zcml
jalon/pas/bdd/install.py
jalon/pas/bdd/interface.py
jalon/pas/bdd/plugin.py
jalon/pas/bdd/tests.py
jalon/pas/bdd/browser/__init__.py
jalon/pas/bdd/browser/add_plugin.zpt
jalon/pas/bdd/browser/configure.zcml
jalon/pas/bdd/browser/icon.gif
jalon/pas/bdd/plugins/__init__.py