Metadata-Version: 1.1
Name: jalon.pas.bdd
Version: 1.0r131
Summary: UNKNOWN
Home-page: http://unice.fr
Author: Bordonado Christophe - Université Nice Sophia Antipolis (UNS Service PI)
Author-email: tice@unice.fr
License: CECILL
Platform: UNKNOWN
Classifier: Framework :: Plone
Classifier: Intended Audience :: Developers
Classifier: License :: OSI Approved :: GNU General Public License (GPL)
